earnix_elevate-0.61.0.dist-info/METADATA
earnix_elevate-0.61.0.dist-info/WHEEL
earnix_elevate-0.61.0.dist-info/entry_points.txt
earnix_elevate-0.61.0.dist-info/licenses/LICENSE
earnix_elevate/THIRD_PARTY_LICENSES.txt
earnix_elevate/__init__.py
earnix_elevate/clients/__init__.py
earnix_elevate/clients/data/__init__.py
earnix_elevate/clients/data/api/__init__.py
earnix_elevate/clients/data/api/ai_assistant_service_api.py
earnix_elevate/clients/data/api/data_table_service_api.py
earnix_elevate/clients/data/api/dataset_service_api.py
earnix_elevate/clients/data/api/export_job_service_api.py
earnix_elevate/clients/data/api_client.py
earnix_elevate/clients/data/api_response.py
earnix_elevate/clients/data/configuration.py
earnix_elevate/clients/data/exceptions.py
earnix_elevate/clients/data/models/__init__.py
earnix_elevate/clients/data/models/add_dataset_data_table_node_request.py
earnix_elevate/clients/data/models/add_dataset_node_request.py
earnix_elevate/clients/data/models/add_dataset_recipe_node_request.py
earnix_elevate/clients/data/models/connection_details_response.py
earnix_elevate/clients/data/models/conversation_id_response.py
earnix_elevate/clients/data/models/conversation_message_response.py
earnix_elevate/clients/data/models/conversation_response.py
earnix_elevate/clients/data/models/create_data_table_request.py
earnix_elevate/clients/data/models/create_dataset_request.py
earnix_elevate/clients/data/models/create_dataset_version_request.py
earnix_elevate/clients/data/models/create_recipe_request.py
earnix_elevate/clients/data/models/data_table_response.py
earnix_elevate/clients/data/models/data_tables_response.py
earnix_elevate/clients/data/models/data_version_response.py
earnix_elevate/clients/data/models/data_version_status_response.py
earnix_elevate/clients/data/models/dataset_data_table_node_response.py
earnix_elevate/clients/data/models/dataset_edge_response.py
earnix_elevate/clients/data/models/dataset_edges_response.py
earnix_elevate/clients/data/models/dataset_node_response.py
earnix_elevate/clients/data/models/dataset_nodes_response.py
earnix_elevate/clients/data/models/dataset_recipe_node_response.py
earnix_elevate-0.61.0.dist-info/RECORD
