Metadata-Version: 2.1
Name: earnix-elevate
Version: 0.61.0
Summary: Earnix Elevate SDK
Keywords: sdk,fintech,insurance,banking
Author-Email: "Earnix Ltd." <info@earnix.com>
License:                                  Apache License
Classifier: Topic :: Software Development :: Libraries :: Python Modules
Classifier: Intended Audience :: Developers
Classifier: Intended Audience :: Financial and Insurance Industry
Classifier: Intended Audience :: Science/Research
Classifier: Programming Language :: Python :: 3.9
Classifier: Programming Language :: Python :: 3.10
Classifier: Programming Language :: Python :: 3.11
Classifier: Programming Language :: Python :: 3.12
Classifier: Programming Language :: Python :: 3.13
Project-URL: Homepage, https://earnix.com
Project-URL: Documentation, https://content.e2.earnix.com/sdk/
Requires-Python: <3.14,>=3.9
Requires-Dist: python-dateutil>=2.8.2
Requires-Dist: typing-extensions>=4.12.2
Requires-Dist: urllib3>=2.0.2
Requires-Dist: pydantic<3,>=2.9.2
Requires-Dist: pyjwt>=2.10.1
Requires-Dist: aenum>=3.1.11
